assist/__init__.py
assist/cli.py
assist/main.py
assist/mcp_manager.py
assist/plugin.py
local_ai_utils_assist-0.2.4.dist-info/licenses/LICENSE
local_ai_utils_assist-0.2.4.dist-info/METADATA
local_ai_utils_assist-0.2.4.dist-info/WHEEL
local_ai_utils_assist-0.2.4.dist-info/entry_points.txt
local_ai_utils_assist-0.2.4.dist-info/top_level.txt
local_ai_utils_assist-0.2.4.dist-info/RECORD
